mhr/__init__.py
mhr-0.1.0.post0.dist-info/METADATA
mhr-0.1.0.post0.dist-info/WHEEL
mhr-0.1.0.post0.dist-info/RECORD
