Metadata-Version: 2.4
Name: mhr
Version: 0.1.0.post0
Summary: Momentum Human Rig
Project-URL: Homepage, https://github.com/facebookresearch/MHR
Project-URL: Repository, https://github.com/facebookresearch/MHR
Author: MHR Contributors
License: MIT
Requires-Python: >=3.12
Requires-Dist: pymomentum-gpu>=0.1.84
Requires-Dist: scikit-learn<2,>=1.7.2
Requires-Dist: smplx<0.2,>=0.1.28
Requires-Dist: torch
Requires-Dist: tqdm<5,>=4.67.1
Requires-Dist: trimesh<5,>=4.8.3
